em_fares_to_xml-2.3.0.dist-info/METADATA
em_fares_to_xml-2.3.0.dist-info/WHEEL
em_fares_to_xml/__init__.py
em_fares_to_xml/em_fares_to_xml.cpython-312-x86_64-linux-gnu.so
em_fares_to_xml-2.3.0.dist-info/RECORD
