Metadata-Version: 2.4
Name: em_fares_to_xml
Version: 2.3.0
Author: Raydel Miranda <raydel.gomez@everymundo.com>, Anahi Martinez <anahi@everymundo.com>
Author-email: Raydel Miranda <raydel.gomez@everymundo.com>, Anahi Martinez <anahi@everymundo.com>
